odoo/addons/account_move_default_journal/README.rst
odoo/addons/account_move_default_journal/__init__.py
odoo/addons/account_move_default_journal/__manifest__.py
odoo/addons/account_move_default_journal/i18n/account_move_default_journal.pot
odoo/addons/account_move_default_journal/i18n/it.po
odoo/addons/account_move_default_journal/models/__init__.py
odoo/addons/account_move_default_journal/models/account_config_settings.py
odoo/addons/account_move_default_journal/models/account_move.py
odoo/addons/account_move_default_journal/models/res_company.py
odoo/addons/account_move_default_journal/readme/CONTRIBUTORS.rst
odoo/addons/account_move_default_journal/readme/DESCRIPTION.rst
odoo/addons/account_move_default_journal/static/description/icon.png
odoo/addons/account_move_default_journal/static/description/index.html
odoo/addons/account_move_default_journal/tests/__init__.py
odoo/addons/account_move_default_journal/tests/test_defaults.py
odoo/addons/account_move_default_journal/views/account_config_settings.xml
odoo/addons/account_move_default_journal/views/res_company_views.xml
odoo14_addon_account_move_default_journal-14.0.1.0.1.dev4.dist-info/METADATA
odoo14_addon_account_move_default_journal-14.0.1.0.1.dev4.dist-info/WHEEL
odoo14_addon_account_move_default_journal-14.0.1.0.1.dev4.dist-info/top_level.txt
odoo14_addon_account_move_default_journal-14.0.1.0.1.dev4.dist-info/RECORD
